dogblack/__init__.py
dogblack/app.py
dogblack-0.1.2.dist-info/METADATA
dogblack-0.1.2.dist-info/WHEEL
dogblack-0.1.2.dist-info/RECORD
