Metadata-Version: 2.1
Name: dogblack
Version: 0.1.2
Summary: DogBlack é um framework web Python que permite criar aplicativos da web com suporte a autenticação, banco de dados MongoDB, servir arquivos estáticos e renderizar templates Jinja2. Ele também fornece um sistema de roteamento simples.
Author: Bruno Ragner
Author-email: brunooragnner@gmail.com
Requires-Python: >=3.11,<4.0
Classifier: Programming Language :: Python :: 3
Classifier: Programming Language :: Python :: 3.11
Requires-Dist: jinja2 (>=3.0,<4.0)
Requires-Dist: pymongo (>=3.11,<4.0)
Requires-Dist: werkzeug (>=2.0,<3.0)
